scrapling_fetch_mcp/__init__.py
scrapling_fetch_mcp/_fetcher.py
scrapling_fetch_mcp/_markdownify.py
scrapling_fetch_mcp/_scrapling.py
scrapling_fetch_mcp/mcp.py
scrapling_fetch_mcp/tools.py
scrapling_fetch_mcp-0.1.6.dist-info/METADATA
scrapling_fetch_mcp-0.1.6.dist-info/WHEEL
scrapling_fetch_mcp-0.1.6.dist-info/entry_points.txt
scrapling_fetch_mcp-0.1.6.dist-info/licenses/LICENSE
scrapling_fetch_mcp-0.1.6.dist-info/RECORD
