Metadata-Version: 2.4
Name: scrapling-fetch-mcp
Version: 0.1.6
Summary: Helps AI assistants access text content from bot-protected websites. MCP server that fetches HTML/markdown from sites with anti-automation measures using Scrapling.
Project-URL: Homepage, https://github.com/cyberchitta/scrapling-fetch-mcp
Project-URL: Bug Tracker, https://github.com/cyberchitta/scrapling-fetch-mcp/issues
Author-email: restlessronin <88921269+restlessronin@users.noreply.github.com>
License:                                  Apache License
License-File: LICENSE
Classifier: Operating System :: OS Independent
Classifier: Programming Language :: Python :: 3
Requires-Python: >=3.10
Requires-Dist: beautifulsoup4>=4.13.3
Requires-Dist: lxml>=5.3.1
Requires-Dist: markdownify>=1.1.0
Requires-Dist: mcp>=1.4.0
Requires-Dist: packaging<25.0,>=24.1
Requires-Dist: scrapling>=0.2.98
